[
  {
    "id": "100100",
    "luggages": []
  },
  {
    "id": "100101",
    "luggages": []
  },
  {
    "id": "100102",
    "luggages": []
  },
  {
    "id": "100103",
    "luggages": []
  },
  {
    "id": "100104",
    "luggages": []
  },
  {
    "id": "100105",
    "luggages": []
  },
  {
    "id": "100200",
    "luggages": []
  },
  {
    "id": "100201",
    "luggages": []
  },
  {
    "id": "100202",
    "luggages": []
  },
  {
    "id": "100203",
    "luggages": []
  },
  {
    "id": "100300",
    "luggages": []
  },
  {
    "id": "100301",
    "luggages": []
  },
  {
    "id": "100302",
    "luggages": []
  },
  {
    "id": "100303",
    "luggages": []
  },
  {
    "id": "100304",
    "luggages": []
  },
  {
    "id": "100100",
    "luggages": [
      {
        "id": "1000000000000000000000000000009",
        "weight": 14,
        "ticketId": "1000000000000000000000000000009"
      }
    ]
  },
  {
    "id": "100100",
    "luggages": [
      {
        "id": "1000000000000000000000000000009",
        "weight": 14,
        "ticketId": "1000000000000000000000000000009"
      },
      {
        "id": "1000000000000000000000000000009",
        "weight": 21,
        "ticketId": "1000000000000000000000000000009"
      }
    ]
  },
  {
    "id": "100100",
    "luggages": [
      {
        "id": "1000000000000000000000000000010",
        "weight": 2,
        "ticketId": "1000000000000000000000000000010"
      }
    ]
  },
  {
    "id": "100100",
    "luggages": [
      {
        "id": "1000000000000000000000000000010",
        "weight": 2,
        "ticketId": "1000000000000000000000000000010"
      },
      {
        "id": "1000000000000000000000000000010",
        "weight": 56,
        "ticketId": "1000000000000000000000000000010"
      }
    ]
  },
  {
    "id": "100100",
    "luggages": [
      {
        "id": "1000000000000000000000000000011",
        "weight": 10,
        "ticketId": "1000000000000000000000000000011"
      }
    ]
  },
  {
    "id": "100500",
    "luggages": []
  },
  {
    "id": "100501",
    "luggages": []
  },
  {
    "id": "100502",
    "luggages": []
  },
  {
    "id": "100503",
    "luggages": []
  },
  {
    "id": "100504",
    "luggages": []
  },
  {
    "id": "100400",
    "luggages": []
  },
  {
    "id": "100401",
    "luggages": []
  },
  {
    "id": "100402",
    "luggages": []
  },
  {
    "id": "100403",
    "luggages": []
  },
  {
    "id": "100404",
    "luggages": []
  },
  {
    "id": "100405",
    "luggages": []
  },
  {
    "id": "100406",
    "luggages": []
  },
  {
    "id": "100407",
    "luggages": []
  },
  {
    "id": "100200",
    "luggages": [
      {
        "id": "1000000000000000000000000000012",
        "weight": 12,
        "ticketId": "1000000000000000000000000000012"
      }
    ]
  },
  {
    "id": "100200",
    "luggages": [
      {
        "id": "1000000000000000000000000000012",
        "weight": 12,
        "ticketId": "1000000000000000000000000000012"
      },
      {
        "id": "1000000000000000000000000000012",
        "weight": 14,
        "ticketId": "1000000000000000000000000000012"
      }
    ]
  },
  {
    "id": "100200",
    "luggages": [
      {
        "id": "1000000000000000000000000000013",
        "weight": 14,
        "ticketId": "1000000000000000000000000000013"
      }
    ]
  },
  {
    "id": "100200",
    "luggages": [
      {
        "id": "1000000000000000000000000000013",
        "weight": 14,
        "ticketId": "1000000000000000000000000000013"
      },
      {
        "id": "1000000000000000000000000000013",
        "weight": 54,
        "ticketId": "1000000000000000000000000000013"
      }
    ]
  },
  {
    "id": "100600",
    "luggages": []
  },
  {
    "id": "100601",
    "luggages": []
  },
  {
    "id": "100602",
    "luggages": []
  },
  {
    "id": "100603",
    "luggages": []
  },
  {
    "id": "100604",
    "luggages": []
  },
  {
    "id": "100605",
    "luggages": []
  },
  {
    "id": "100606",
    "luggages": []
  },
  {
    "id": "100607",
    "luggages": []
  }
]